LICENSE
MANIFEST.in
README
README.md
requirements.txt
setup.cfg
setup.py
feedwarrior/__init__.py
feedwarrior/common.py
feedwarrior/config.py
feedwarrior/entry.py
feedwarrior/error.py
feedwarrior/feed.py
feedwarrior.egg-info/PKG-INFO
feedwarrior.egg-info/SOURCES.txt
feedwarrior.egg-info/dependency_links.txt
feedwarrior.egg-info/entry_points.txt
feedwarrior.egg-info/requires.txt
feedwarrior.egg-info/top_level.txt
feedwarrior/adapters/__init__.py
feedwarrior/adapters/couchdbadapter.py
feedwarrior/adapters/fileadapter.py
feedwarrior/cmd/__init__.py
feedwarrior/cmd/add.py
feedwarrior/cmd/attach.py
feedwarrior/cmd/create.py
feedwarrior/cmd/entry.py
feedwarrior/cmd/ls.py
feedwarrior/cmd/show.py
feedwarrior/runnable/main.py
man/man1/feedwarrior.1
scripts/feedwarrior
test/test_couchdb.py
test/test_file.py
test/test_multi.py