Metadata-Version: 2.1
Name: feedwarrior
Version: 0.5.7
Summary: Feeds, warrior style
Home-page: https://holbrook.no/src/feedwarrior/log.html
Author: Louis Holbrook
Author-email: dev@holbrook.no
License: GPLv3+
Keywords: feed,log,worklog
Classifier: Programming Language :: Python :: 3
Classifier: Operating System :: OS Independent
Classifier: Development Status :: 3 - Alpha
Classifier: Environment :: Console
Classifier: Intended Audience :: Developers
Classifier: Topic :: Utilities
Classifier: License :: OSI Approved :: GNU Lesser General Public License v3 or later (LGPLv3+)
License-File: LICENSE
Requires-Dist: pyxdg~=0.26
Requires-Dist: tasklib<2.0.0,>=1.3.0
Requires-Dist: filemagic~=1.6
Requires-Dist: mime_parser~=1.2.0
